ryteboxformat/.DS_Store
ryteboxformat/Config Master 081424.xlsx
ryteboxformat/MRI_to_RyteBox_Formatter_082224.py
ryteboxformat/TestWXPython.py
ryteboxformat/app.log
ryteboxformat/main.py
ryteboxformat/output_file.xlsx
ryteboxformat/requirements.txt
ryteboxformat/~$Config Master 081424.xlsx
ryteboxformat-2.2.dist-info/METADATA
ryteboxformat-2.2.dist-info/WHEEL
ryteboxformat-2.2.dist-info/RECORD
